cirq_scaleway/__init__.py
cirq_scaleway/scaleway_device.py
cirq_scaleway/scaleway_service.py
cirq_scaleway/scaleway_session.py
cirq_scaleway/versions.py
cirq_scaleway-0.1.14.dist-info/licenses/LICENSE
cirq_scaleway-0.1.14.dist-info/METADATA
cirq_scaleway-0.1.14.dist-info/WHEEL
cirq_scaleway-0.1.14.dist-info/top_level.txt
cirq_scaleway-0.1.14.dist-info/RECORD
