Metadata-Version: 2.4
Name: cirq_scaleway
Version: 0.1.14
Summary: A Cirq package to connect to Scaleway Quantum as a Service
Author: The Scaleway Developers
Author-email: vmacheret@scaleway.com
License: Apache 2
Project-URL: Documentation, https://www.scaleway.com/en/quantum-as-a-service/
Project-URL: Source, https://github.com/scaleway/cirq-scaleway
Project-URL: Tracker, https://github.com/scaleway/cirq-scaleway/issues
Requires-Python: >=3.12.0
License-File: LICENSE
Requires-Dist: pandas==2.3.1
Requires-Dist: cirq-core>=1.3.0
Requires-Dist: scaleway-qaas-client>=0.1.16
Requires-Dist: qio>=0.1.17
Dynamic: author
Dynamic: author-email
Dynamic: description
Dynamic: license
Dynamic: license-file
Dynamic: project-url
Dynamic: requires-dist
Dynamic: requires-python
Dynamic: summary
